langchain_postgres/__init__.py
langchain_postgres/_utils.py
langchain_postgres/chat_message_histories.py
langchain_postgres/checkpoint.py
langchain_postgres/py.typed
langchain_postgres/vectorstores.py
gigachain_postgres-0.1.3.dist-info/LICENSE
gigachain_postgres-0.1.3.dist-info/METADATA
gigachain_postgres-0.1.3.dist-info/WHEEL
gigachain_postgres-0.1.3.dist-info/RECORD
