Metadata-Version: 2.1
Name: gigachain-postgres
Version: 0.1.3
Summary: An integration package connecting Upstage and gigachain
Home-page: https://github.com/langchain-ai/langchain
License: MIT
Requires-Python: >=3.8.1,<4.0
Classifier: License :: OSI Approved :: MIT License
Classifier: Programming Language :: Python :: 3
Classifier: Programming Language :: Python :: 3.9
Classifier: Programming Language :: Python :: 3.10
Classifier: Programming Language :: Python :: 3.11
Classifier: Programming Language :: Python :: 3.12
Requires-Dist: gigachain-core (>=0.1.44,<0.2.0)
Requires-Dist: gigachain-openai (>=0.1.3,<0.2.0)
Requires-Dist: pymupdf (>=1.24.1,<2.0.0)
Requires-Dist: requests (>=2.31.0,<3.0.0)
Project-URL: Repository, https://github.com/langchain-ai/langchain
Project-URL: Source Code, https://github.com/langchain-ai/langchain/tree/master/libs/partners/upstage
